<?xml version = '1.0' encoding = 'UTF-8'?>
<TableProxyOraclev11g class="oracle.dbtools.crest.model.design.storage.oracle.v11g.TableProxyOraclev11g" name="LOCALITATI" id="D5A691B0-4367-2347-0FF6-71D7ED8A1081" directorySegmentName="seg_0">
   <createdBy>catalin.strimbei</createdBy>
   <createdTime>2011-04-20 12:49:04 UTC</createdTime>
   <changedBy>catalin.strimbei</changedBy>
   <changedTime>2011-04-20 12:49:06 UTC</changedTime>
   <ownerDesignName>Admitere-DM</ownerDesignName>
   <logging>YES</logging>
   <partitionedRowMovement>DISABLE</partitionedRowMovement>
   <segment>ADE8F0EC-DD55-9DC3-0891-729656B52B48</segment>
   <tableSpace>BE5832D7-DB55-7383-2FCD-1DE689BAF37A</tableSpace>
   <columnProxies>
      <ColumnProxy class="oracle.dbtools.crest.model.design.storage.oracle.v11g.ColumnProxyOraclev11g" name="JUD" id="3DDE945C-303A-5964-C3AC-9C2E616CAD7F">
         <createdBy>catalin.strimbei</createdBy>
         <createdTime>2011-04-20 12:49:04 UTC</createdTime>
         <changedBy>catalin.strimbei</changedBy>
         <changedTime>2011-04-20 12:49:04 UTC</changedTime>
         <ownerDesignName>Admitere-DM</ownerDesignName>
      </ColumnProxy>
      <ColumnProxy class="oracle.dbtools.crest.model.design.storage.oracle.v11g.ColumnProxyOraclev11g" name="MEDIU" id="6D4C0386-B983-FCFC-04D6-33BC3C15EAF1">
         <createdBy>catalin.strimbei</createdBy>
         <createdTime>2011-04-20 12:49:04 UTC</createdTime>
         <changedBy>catalin.strimbei</changedBy>
         <changedTime>2011-04-20 12:49:05 UTC</changedTime>
         <ownerDesignName>Admitere-DM</ownerDesignName>
         <defaultValue>&amp;apos;U&amp;apos; </defaultValue>
         <validate>NO</validate>
      </ColumnProxy>
      <ColumnProxy class="oracle.dbtools.crest.model.design.storage.oracle.v11g.ColumnProxyOraclev11g" name="CODPOSTNOU" id="EC511A95-7DFC-3E4B-3901-083A7585AE86">
         <createdBy>catalin.strimbei</createdBy>
         <createdTime>2011-04-20 12:49:04 UTC</createdTime>
         <changedBy>catalin.strimbei</changedBy>
         <changedTime>2011-04-20 12:49:04 UTC</changedTime>
         <ownerDesignName>Admitere-DM</ownerDesignName>
      </ColumnProxy>
      <ColumnProxy class="oracle.dbtools.crest.model.design.storage.oracle.v11g.ColumnProxyOraclev11g" name="CODPOSTVECHI" id="ED2E79B6-98F2-73BB-88CB-4BA798270294">
         <createdBy>catalin.strimbei</createdBy>
         <createdTime>2011-04-20 12:49:04 UTC</createdTime>
         <changedBy>catalin.strimbei</changedBy>
         <changedTime>2011-04-20 12:49:04 UTC</changedTime>
         <ownerDesignName>Admitere-DM</ownerDesignName>
      </ColumnProxy>
      <ColumnProxy class="oracle.dbtools.crest.model.design.storage.oracle.v11g.ColumnProxyOraclev11g" name="LOCALITATE" id="FABF27BD-3E69-A365-D563-E9746F05FE24">
         <createdBy>catalin.strimbei</createdBy>
         <createdTime>2011-04-20 12:49:04 UTC</createdTime>
         <changedBy>catalin.strimbei</changedBy>
         <changedTime>2011-04-20 12:49:04 UTC</changedTime>
         <ownerDesignName>Admitere-DM</ownerDesignName>
      </ColumnProxy>
      <ColumnProxy class="oracle.dbtools.crest.model.design.storage.oracle.v11g.ColumnProxyOraclev11g" name="IDLOC" id="FBCACAD6-A574-CA07-43BF-3DF319ABF01D">
         <createdBy>catalin.strimbei</createdBy>
         <createdTime>2011-04-20 12:49:04 UTC</createdTime>
         <changedBy>catalin.strimbei</changedBy>
         <changedTime>2011-04-20 12:49:04 UTC</changedTime>
         <ownerDesignName>Admitere-DM</ownerDesignName>
      </ColumnProxy>
   </columnProxies>
   <foreignKeys>
      <ForeignKey class="oracle.dbtools.crest.model.design.storage.oracle.v10g.FKProxyOraclev10g" name="FK_LOCALITATI_JUDETE" id="848F1309-C3CE-A933-F060-615206EBB981">
         <createdBy>catalin.strimbei</createdBy>
         <createdTime>2011-04-20 12:49:06 UTC</createdTime>
         <changedBy>catalin.strimbei</changedBy>
         <changedTime>2011-04-20 12:49:06 UTC</changedTime>
         <ownerDesignName>Admitere-DM</ownerDesignName>
      </ForeignKey>
   </foreignKeys>
   <primaryKeys>
      <PrimaryKey class="oracle.dbtools.crest.model.design.storage.oracle.v10g.PKProxyOraclev10g" name="PK_LOCALITATI" id="C84238D3-2574-6186-3052-99AACB7A6755">
         <createdBy>catalin.strimbei</createdBy>
         <createdTime>2011-04-20 12:49:05 UTC</createdTime>
         <changedBy>catalin.strimbei</changedBy>
         <changedTime>2011-04-20 12:49:05 UTC</changedTime>
         <ownerDesignName>Admitere-DM</ownerDesignName>
         <indexSort>NO</indexSort>
      </PrimaryKey>
   </primaryKeys>
</TableProxyOraclev11g>