<?xml version = '1.0' encoding = 'UTF-8'?>
<TableProxyOraclev11g class="oracle.dbtools.crest.model.design.storage.oracle.v11g.TableProxyOraclev11g" name="ORDINE" id="E43EED4C-C215-F1E2-24EE-9848E0DDE135" directorySegmentName="seg_0">
   <createdBy>catalin.strimbei</createdBy>
   <createdTime>2011-04-20 12:49:04 UTC</createdTime>
   <changedBy>catalin.strimbei</changedBy>
   <changedTime>2011-04-20 12:49:05 UTC</changedTime>
   <ownerDesignName>Admitere-DM</ownerDesignName>
   <logging>NO</logging>
   <partitionedRowMovement>DISABLE</partitionedRowMovement>
   <segment>B0F075B5-536F-0617-12A8-06FBDE58B758</segment>
   <temporary>YES</temporary>
   <columnProxies>
      <ColumnProxy class="oracle.dbtools.crest.model.design.storage.oracle.v11g.ColumnProxyOraclev11g" name="PRIORITATE" id="1F6F8A92-E6BC-90E2-6117-96DEB1BFAC79">
         <createdBy>catalin.strimbei</createdBy>
         <createdTime>2011-04-20 12:49:05 UTC</createdTime>
         <changedBy>catalin.strimbei</changedBy>
         <changedTime>2011-04-20 12:49:05 UTC</changedTime>
         <ownerDesignName>Admitere-DM</ownerDesignName>
      </ColumnProxy>
      <ColumnProxy class="oracle.dbtools.crest.model.design.storage.oracle.v11g.ColumnProxyOraclev11g" name="MEDIE" id="360253BF-54BA-FAA6-B46E-22A7DFCB7130">
         <createdBy>catalin.strimbei</createdBy>
         <createdTime>2011-04-20 12:49:05 UTC</createdTime>
         <changedBy>catalin.strimbei</changedBy>
         <changedTime>2011-04-20 12:49:05 UTC</changedTime>
         <ownerDesignName>Admitere-DM</ownerDesignName>
      </ColumnProxy>
      <ColumnProxy class="oracle.dbtools.crest.model.design.storage.oracle.v11g.ColumnProxyOraclev11g" name="ORDINE" id="89AC5DD0-E49F-4AA3-AFA9-DA553563C4FB">
         <createdBy>catalin.strimbei</createdBy>
         <createdTime>2011-04-20 12:49:05 UTC</createdTime>
         <changedBy>catalin.strimbei</changedBy>
         <changedTime>2011-04-20 12:49:05 UTC</changedTime>
         <ownerDesignName>Admitere-DM</ownerDesignName>
      </ColumnProxy>
      <ColumnProxy class="oracle.dbtools.crest.model.design.storage.oracle.v11g.ColumnProxyOraclev11g" name="TAXA" id="AEA94DF4-EAE4-D422-4761-AFAE5CCF8F2B">
         <createdBy>catalin.strimbei</createdBy>
         <createdTime>2011-04-20 12:49:05 UTC</createdTime>
         <changedBy>catalin.strimbei</changedBy>
         <changedTime>2011-04-20 12:49:05 UTC</changedTime>
         <ownerDesignName>Admitere-DM</ownerDesignName>
      </ColumnProxy>
      <ColumnProxy class="oracle.dbtools.crest.model.design.storage.oracle.v11g.ColumnProxyOraclev11g" name="IDFISA" id="C4AE66B8-7705-0F46-E492-18A1E10B1766">
         <createdBy>catalin.strimbei</createdBy>
         <createdTime>2011-04-20 12:49:05 UTC</createdTime>
         <changedBy>catalin.strimbei</changedBy>
         <changedTime>2011-04-20 12:49:05 UTC</changedTime>
         <ownerDesignName>Admitere-DM</ownerDesignName>
      </ColumnProxy>
      <ColumnProxy class="oracle.dbtools.crest.model.design.storage.oracle.v11g.ColumnProxyOraclev11g" name="SPEC" id="E1D8B770-8F8A-ABDB-CC8B-0C7DFEA878F5">
         <createdBy>catalin.strimbei</createdBy>
         <createdTime>2011-04-20 12:49:05 UTC</createdTime>
         <changedBy>catalin.strimbei</changedBy>
         <changedTime>2011-04-20 12:49:05 UTC</changedTime>
         <ownerDesignName>Admitere-DM</ownerDesignName>
      </ColumnProxy>
      <ColumnProxy class="oracle.dbtools.crest.model.design.storage.oracle.v11g.ColumnProxyOraclev11g" name="ATESTAT" id="E949B1AA-32F7-B53B-E9A3-BC245417FABE">
         <createdBy>catalin.strimbei</createdBy>
         <createdTime>2011-04-20 12:49:05 UTC</createdTime>
         <changedBy>catalin.strimbei</changedBy>
         <changedTime>2011-04-20 12:49:05 UTC</changedTime>
         <ownerDesignName>Admitere-DM</ownerDesignName>
      </ColumnProxy>
   </columnProxies>
</TableProxyOraclev11g>